{
  "id": "navigation_item",
  "type": "SharedSlice",
  "name": "NavigationItem",
  "description": "NavigationItem",
  "variations": [
    {
      "id": "default",
      "name": "Default",
      "docURL": "...",
      "version": "initial",
      "description": "Default",
      "imageUrl": "",
      "primary": {
        "link": {
          "type": "Link",
          "config": {
            "label": "link",
            "placeholder": "",
            "allowTargetBlank": true,
            "select": null,
            "allowText": true
          }
        },
        "child_link": {
          "type": "Group",
          "config": {
            "label": "child link",
            "repeat": true,
            "fields": {
              "link": {
                "type": "Link",
                "config": {
                  "label": "link",
                  "placeholder": "",
                  "allowTargetBlank": true,
                  "select": null,
                  "allowText": true
                }
              }
            }
          }
        }
      },
      "items": {}
    }
  ]
}